instant_api/__init__.py
instant_api/instant_api.py
instant_api/version.py
instant_api-0.2.0.dist-info/LICENSE.txt
instant_api-0.2.0.dist-info/METADATA
instant_api-0.2.0.dist-info/WHEEL
instant_api-0.2.0.dist-info/top_level.txt
instant_api-0.2.0.dist-info/RECORD
