Metadata-Version: 2.1
Name: instant-api
Version: 0.2.0
Summary: Instantly create an HTTP API with automatic type conversions, JSON RPC, and a Swagger UI. Just add methods!
Home-page: http://github.com/alexmojaki/instant_api
Author: Alex Hall
Author-email: alex.mojaki@gmail.com
License: MIT
Platform: UNKNOWN
Classifier: Intended Audience :: Developers
Classifier: Programming Language :: Python :: 3
Classifier: Programming Language :: Python :: 3.7
Classifier: Programming Language :: Python :: 3.8
Classifier: Programming Language :: Python :: 3.9
Classifier: Framework :: Flask
Classifier: Topic :: Internet
Classifier: Topic :: Internet :: WWW/HTTP
Classifier: Topic :: Internet :: WWW/HTTP :: HTTP Servers
Classifier: Topic :: Internet :: WWW/HTTP :: WSGI :: Server
Classifier: License :: OSI Approved :: MIT License
Classifier: Operating System :: OS Independent
Requires-Dist: flasgger
Requires-Dist: json-rpc
Requires-Dist: datafunctions
Requires-Dist: apispec
Provides-Extra: client
Requires-Dist: instant-client[requests] ; extra == 'client'
Provides-Extra: tests
Requires-Dist: pytest ; extra == 'tests'
Requires-Dist: instant-client[requests] ; extra == 'tests'
Requires-Dist: littleutils ; extra == 'tests'
